fmc/__init__.py
fmc/app.py
fmc/tasks/__init__.py
fmc/tasks/cheatsheet.py
fmc/tasks/git.py
fmc/tasks/go.py
fmc/tasks/info.py
fmc/tasks/init.py
fmc/tasks/secure.py
fmc/utils/__init__.py
fmc/utils/config_manager.py
fmc/utils/logger_formatter.py
fmc/utils/misc.py
fmc-0.2.0.dist-info/LICENSE
fmc-0.2.0.dist-info/METADATA
fmc-0.2.0.dist-info/WHEEL
fmc-0.2.0.dist-info/entry_points.txt
fmc-0.2.0.dist-info/top_level.txt
fmc-0.2.0.dist-info/RECORD
