Metadata-Version: 2.1
Name: fmc
Version: 0.2.0
Summary: fmc is a simple cli application for one's own convenience.
Home-page: UNKNOWN
Author: Ming Feng
Author-email: fengming@mail.com
License: MIT
Keywords: fmc,shortcut,alias
Platform: UNKNOWN
Classifier: Development Status :: 4 - Beta
Classifier: License :: OSI Approved :: MIT License
Classifier: Programming Language :: Python
Classifier: Programming Language :: Python :: 3.8
Classifier: Topic :: Software Development :: Libraries
Classifier: Topic :: Software Development :: Libraries :: Python Modules
Classifier: Intended Audience :: Developers
Requires-Python: >=3.8
Requires-Dist: plumbum (==1.6.9)
